jos3/__init__.py
jos3/comfmod.py
jos3/construction.py
jos3/jos3.py
jos3/matrix.py
jos3/params.py
jos3/thermoregulation.py
jos3-0.5.0.dist-info/LICENSE
jos3-0.5.0.dist-info/METADATA
jos3-0.5.0.dist-info/WHEEL
jos3-0.5.0.dist-info/top_level.txt
jos3-0.5.0.dist-info/RECORD
