Metadata-Version: 2.1
Name: jos3
Version: 0.5.0
Summary: Joint-thermoregulation system, JOS-3
Home-page: https://github.com/TanabeLab/JOS-3
Author: Yoshito Takahashi
Author-email: takahashiyoshito64@gmail.com
License: MIT
Platform: UNKNOWN
Classifier: Operating System :: OS Independent
Classifier: Intended Audience :: Science/Research
Classifier: Intended Audience :: Education
Classifier: Programming Language :: Python :: 3
Classifier: Programming Language :: Python :: 3.6
Classifier: Programming Language :: Python :: 3.7
Classifier: Programming Language :: Python :: 3.8
Classifier: Programming Language :: Python :: 3.9
Classifier: Programming Language :: Python :: Implementation :: CPython
Classifier: License :: OSI Approved :: MIT License
License-File: LICENSE
